elastalert/__init__.py
elastalert/alerts.py
elastalert/auth.py
elastalert/config.py
elastalert/create_index.py
elastalert/elastalert.py
elastalert/enhancements.py
elastalert/eql.py
elastalert/kibana_discover.py
elastalert/kibana_external_url_formatter.py
elastalert/loaders.py
elastalert/opensearch_discover.py
elastalert/opensearch_external_url_formatter.py
elastalert/prometheus_wrapper.py
elastalert/ruletypes.py
elastalert/schema.yaml
elastalert/test_rule.py
elastalert/util.py
elastalert/yaml.py
elastalert/alerters/__init__.py
elastalert/alerters/alerta.py
elastalert/alerters/alertmanager.py
elastalert/alerters/chatwork.py
elastalert/alerters/command.py
elastalert/alerters/datadog.py
elastalert/alerters/debug.py
elastalert/alerters/dingtalk.py
elastalert/alerters/discord.py
elastalert/alerters/email.py
elastalert/alerters/exotel.py
elastalert/alerters/flashduty.py
elastalert/alerters/gelf.py
elastalert/alerters/gitter.py
elastalert/alerters/googlechat.py
elastalert/alerters/httppost.py
elastalert/alerters/httppost2.py
elastalert/alerters/indexer.py
elastalert/alerters/iris.py
elastalert/alerters/jira.py
elastalert/alerters/lark.py
elastalert/alerters/matrixhookshot.py
elastalert/alerters/mattermost.py
elastalert/alerters/opsgenie.py
elastalert/alerters/pagerduty.py
elastalert/alerters/pagertree.py
elastalert/alerters/powerautomate.py
elastalert/alerters/rocketchat.py
elastalert/alerters/servicenow.py
elastalert/alerters/ses.py
elastalert/alerters/slack.py
elastalert/alerters/smseagle.py
elastalert/alerters/sns.py
elastalert/alerters/stomp.py
elastalert/alerters/teams.py
elastalert/alerters/telegram.py
elastalert/alerters/tencentsms.py
elastalert/alerters/thehive.py
elastalert/alerters/twilio.py
elastalert/alerters/victorops.py
elastalert/alerters/webex_webhook.py
elastalert/alerters/workwechat.py
elastalert/alerters/yzj.py
elastalert/alerters/zabbix.py
elastalert/es_mappings/7/elastalert.json
elastalert/es_mappings/7/elastalert_error.json
elastalert2-2.27.0.dist-info/licenses/LICENSE
elastalert2-2.27.0.dist-info/METADATA
elastalert2-2.27.0.dist-info/WHEEL
elastalert2-2.27.0.dist-info/entry_points.txt
elastalert2-2.27.0.dist-info/top_level.txt
elastalert2-2.27.0.dist-info/RECORD
