Metadata-Version: 2.4
Name: elastalert2
Version: 2.27.0
Summary: Automated rule-based alerting for Elasticsearch
Home-page: https://github.com/jertel/elastalert2
License: Apache 2.0
Project-URL: Documentation, https://elastalert2.readthedocs.io
Project-URL: Source Code, https://github.com/jertel/elastalert2
Project-URL: Discussion Forum, https://github.com/jertel/elastalert2/discussions
Classifier: Programming Language :: Python :: 3.12
Classifier: Programming Language :: Python :: 3.13
Classifier: Programming Language :: Python :: 3.14
Classifier: License :: OSI Approved :: Apache Software License
Classifier: Operating System :: OS Independent
Requires-Python: >=3.12
License-File: LICENSE
Requires-Dist: apscheduler<4.0,>=3.11.0
Requires-Dist: aws-requests-auth>=0.4.3
Requires-Dist: boto3>=1.40.59
Requires-Dist: cffi>=2.0.0
Requires-Dist: croniter>=6.0.0
Requires-Dist: elasticsearch==7.10.1
Requires-Dist: envparse>=0.2.0
Requires-Dist: exotel==0.1.5
Requires-Dist: Jinja2>=3.1.6
Requires-Dist: jira>=3.10.5
Requires-Dist: jsonpointer>=3.0.0
Requires-Dist: jsonschema>=4.25.1
Requires-Dist: prettytable>=3.16.0
Requires-Dist: prison>=0.2.1
Requires-Dist: prometheus_client>=0.23.1
Requires-Dist: python-dateutil>=2.9.0.post0
Requires-Dist: PyYAML>=6.0.3
Requires-Dist: py-zabbix>=1.1.7
Requires-Dist: requests>=2.31.0
Requires-Dist: sortedcontainers>=2.4.0
Requires-Dist: statsd-tags==3.2.1.post1
Requires-Dist: stomp.py>=8.2.0
Requires-Dist: tencentcloud-sdk-python>=3.0.1479
Requires-Dist: texttable>=1.7.0
Requires-Dist: twilio>=9.8.4
Dynamic: classifier
Dynamic: description
Dynamic: description-content-type
Dynamic: home-page
Dynamic: license
Dynamic: license-file
Dynamic: project-url
Dynamic: requires-dist
Dynamic: requires-python
Dynamic: summary
